{
    "targets": {
        "0": {},
        "base": {
            "persistent": true
        }
    },
    "custom_passes": {
        "souper_secret_settings:before_layer_render": [
            {
                "vertex_shader": "minecraft:core/screenquad",
                "fragment_shader": "minecraft:post/blit",
                "inputs": [
                    {
                        "sampler_name": "In",
                        "target": "minecraft:main"
                    }
                ],
                "output": "base",
                "uniforms": {
                    "BlitConfig": [
                        {
                            "name": "ColorModulate",
                            "type": "vec4",
                            "value": [ 1.0, 1.0, 1.0, 1.0 ]
                        }
                    ]
                }
            }
        ],
        "souper_secret_settings:after_layer_render": [
            {
                "vertex_shader": "minecraft:core/screenquad",
                "fragment_shader": "soup:post/cross",
                "inputs": [
                    {
                        "sampler_name": "In",
                        "target": "base"
                    },
                    {
                        "sampler_name": "Base",
                        "target": "minecraft:main"
                    }
                ],
                "output": "0",
                "uniforms": {
                    "CrossConfig": [
                        {
                            "name": "Swap",
                            "type": "vec3",
                            "value": [ 0.0, 0.0, 0.0 ]
                        },
                        {
                            "name": "R",
                            "type": "vec4",
                            "value": [ 1.0, 1.0, 0.0, 0.0 ]
                        },
                        {
                            "name": "G",
                            "type": "vec4",
                            "value": [ 1.0, 1.0, 0.0, 0.0 ]
                        },
                        {
                            "name": "B",
                            "type": "vec4",
                            "value": [ 1.0, 1.0, 0.0, 0.0 ]
                        },
                        {
                            "name": "Abs",
                            "type": "vec3",
                            "value": [ 1.0, 1.0, 1.0 ]
                        },
                        {
                            "name": "MinThreshold",
                            "type": "vec3",
                            "value": [ 0.1, 0.1, 0.1 ]
                        },
                        {
                            "name": "MinA",
                            "type": "vec3",
                            "value": [ 0.1, 0.1, 0.1 ]
                        },
                        {
                            "name": "MinB",
                            "type": "vec3",
                            "value": [ 0.0, 0.0, 0.0 ]
                        },
                        {
                            "name": "BaseA",
                            "type": "vec3",
                            "value": [ 0.0, 0.0, 0.0 ]
                        },
                        {
                            "name": "BaseB",
                            "type": "vec3",
                            "value": [ 0.0, 0.0, 0.0 ]
                        },
                        {
                            "name": "Out",
                            "type": "vec3",
                            "value": [ 1.0, 1.0, 1.0 ]
                        }
                    ]
                }
            },
            {
                "vertex_shader": "minecraft:core/screenquad",
                "fragment_shader": "minecraft:post/blit",
                "inputs": [
                    {
                        "sampler_name": "In",
                        "target": "0"
                    }
                ],
                "output": "minecraft:main",
                "uniforms": {
                    "BlitConfig": [
                        {
                            "name": "ColorModulate",
                            "type": "vec4",
                            "value": [ 1.0, 1.0, 1.0, 1.0 ]
                        }
                    ]
                }
            }
        ]
    }
}